orbit_orator/__init__.py
orbit_orator/database_manager.py
orbit_orator/commands/__init__.py
orbit_orator/commands/application.py
orbit_orator/commands/command.py
orbit_orator/commands/migrations/__init__.py
orbit_orator/commands/migrations/base_command.py
orbit_orator/commands/migrations/install_command.py
orbit_orator/commands/migrations/make_command.py
orbit_orator/commands/migrations/migrate_command.py
orbit_orator/commands/migrations/refresh_command.py
orbit_orator/commands/migrations/reset_command.py
orbit_orator/commands/migrations/rollback_command.py
orbit_orator/commands/migrations/status_command.py
orbit_orator/commands/models/__init__.py
orbit_orator/commands/models/make_command.py
orbit_orator/commands/models/stubs.py
orbit_orator/commands/seeds/__init__.py
orbit_orator/commands/seeds/base_command.py
orbit_orator/commands/seeds/make_command.py
orbit_orator/commands/seeds/seed_command.py
orbit_orator/connections/__init__.py
orbit_orator/connections/connection.py
orbit_orator/connections/connection_interface.py
orbit_orator/connections/connection_resolver_interface.py
orbit_orator/connections/mysql_connection.py
orbit_orator/connections/postgres_connection.py
orbit_orator/connections/sqlite_connection.py
orbit_orator/connectors/__init__.py
orbit_orator/connectors/connection_factory.py
orbit_orator/connectors/connector.py
orbit_orator/connectors/mysql_connector.py
orbit_orator/connectors/postgres_connector.py
orbit_orator/connectors/sqlite_connector.py
orbit_orator/dbal/__init__.py
orbit_orator/dbal/abstract_asset.py
orbit_orator/dbal/column.py
orbit_orator/dbal/column_diff.py
orbit_orator/dbal/comparator.py
orbit_orator/dbal/foreign_key_constraint.py
orbit_orator/dbal/identifier.py
orbit_orator/dbal/index.py
orbit_orator/dbal/mysql_schema_manager.py
orbit_orator/dbal/postgres_schema_manager.py
orbit_orator/dbal/schema_manager.py
orbit_orator/dbal/sqlite_schema_manager.py
orbit_orator/dbal/table.py
orbit_orator/dbal/table_diff.py
orbit_orator-0.9.9.15.dist-info/licenses/LICENSE
orbit_orator-0.9.9.15.dist-info/METADATA
orbit_orator-0.9.9.15.dist-info/WHEEL
orbit_orator-0.9.9.15.dist-info/top_level.txt
orbit_orator-0.9.9.15.dist-info/RECORD
