Metadata-Version: 2.4
Name: orbit-orator
Version: 0.9.9.15
Summary: A simple ORM for Python
Home-page: https://github.com/maxiaoyu/orator
Author: Maxiaoyu
Author-email: Maxiaoyu <maxiaoyu@example.com>
License-Expression: MIT
Project-URL: Homepage, https://github.com/maxiaoyu/orator
Project-URL: Repository, https://github.com/maxiaoyu/orator.git
Classifier: Development Status :: 4 - Beta
Classifier: Intended Audience :: Developers
Classifier: Programming Language :: Python :: 3
Classifier: Programming Language :: Python :: 3.8
Classifier: Programming Language :: Python :: 3.9
Classifier: Programming Language :: Python :: 3.10
Classifier: Programming Language :: Python :: 3.11
Classifier: Topic :: Software Development :: Libraries :: Python Modules
Requires-Python: >=3.8
License-File: LICENSE
Requires-Dist: backpack>=0.1
Requires-Dist: blinker>=1.4
Requires-Dist: cleo>=0.6
Requires-Dist: inflection>=0.5.1
Requires-Dist: Faker>=0.8
Requires-Dist: lazy-object-proxy>=1.2
Requires-Dist: pendulum>=2.0
Requires-Dist: pyaml>=16.12
Requires-Dist: pyyaml<7.0,>=5.1
Requires-Dist: Pygments>=2.2
Requires-Dist: simplejson>=3.10
Requires-Dist: six>=1.10
Requires-Dist: wrapt>=1.10
Dynamic: author
Dynamic: home-page
Dynamic: license-file
Dynamic: requires-python
